{
  "commands": {
    "campaign:pull": {
      "aliases": [],
      "args": {
        "id_name_dxid": {
          "description": "it's better to use -i <id> or -x <dxid> or -n <name>, but you can for convenience",
          "hidden": true,
          "name": "id_name_dxid"
        }
      },
      "description": "pull the campaign from the server to the config file",
      "flags": {
        "json": {
          "description": "Format output as json",
          "exclusive": [
            "human",
            "csv"
          ],
          "helpGroup": "OUTPUT",
          "name": "json",
          "allowNo": false,
          "type": "boolean"
        },
        "env": {
          "description": "allow to switch between configurations (server or users)",
          "name": "env",
          "default": "default",
          "hasDynamicHelp": false,
          "multiple": false,
          "type": "option"
        },
        "human": {
          "description": "Format output to be read on screen by a human [default]",
          "helpGroup": "OUTPUT",
          "name": "human",
          "allowNo": false,
          "type": "boolean"
        },
        "csv": {
          "description": "Format output as csv",
          "helpGroup": "OUTPUT",
          "name": "csv",
          "allowNo": false,
          "type": "boolean"
        },
        "simplify": {
          "description": "flatten and filter to output only the most important attributes, mostly relevant for json",
          "helpGroup": "OUTPUT",
          "name": "simplify",
          "allowNo": true,
          "type": "boolean"
        },
        "id": {
          "char": "i",
          "exclusive": [
            "name",
            "dxid"
          ],
          "name": "id",
          "hasDynamicHelp": false,
          "multiple": false,
          "type": "option"
        },
        "dxid": {
          "char": "x",
          "description": "dxid",
          "name": "dxid",
          "hasDynamicHelp": false,
          "multiple": false,
          "type": "option"
        },
        "name": {
          "char": "n",
          "name": "name",
          "hasDynamicHelp": false,
          "multiple": false,
          "type": "option"
        },
        "git": {
          "description": "commit the changes to git",
          "name": "git",
          "allowNo": true,
          "type": "boolean"
        }
      },
      "hasDynamicHelp": false,
      "hiddenAliases": [],
      "id": "campaign:pull",
      "pluginAlias": "@proca/widget",
      "pluginName": "@proca/widget",
      "pluginType": "core",
      "strict": true,
      "isESM": true,
      "relativePath": [
        "bin",
        "commands",
        "campaign",
        "pull.mjs"
      ]
    },
    "campaign:push": {
      "aliases": [],
      "args": {
        "id_name_dxid": {
          "description": "it's better to use -i <id> or -x <dxid> or -n <name>, but you can for convenience",
          "hidden": true,
          "name": "id_name_dxid"
        }
      },
      "description": "push the campaign from the config file to the server",
      "flags": {
        "json": {
          "description": "Format output as json",
          "exclusive": [
            "human",
            "csv"
          ],
          "helpGroup": "OUTPUT",
          "name": "json",
          "allowNo": false,
          "type": "boolean"
        },
        "env": {
          "description": "allow to switch between configurations (server or users)",
          "name": "env",
          "default": "default",
          "hasDynamicHelp": false,
          "multiple": false,
          "type": "option"
        },
        "human": {
          "description": "Format output to be read on screen by a human [default]",
          "helpGroup": "OUTPUT",
          "name": "human",
          "allowNo": false,
          "type": "boolean"
        },
        "csv": {
          "description": "Format output as csv",
          "helpGroup": "OUTPUT",
          "name": "csv",
          "allowNo": false,
          "type": "boolean"
        },
        "simplify": {
          "description": "flatten and filter to output only the most important attributes, mostly relevant for json",
          "helpGroup": "OUTPUT",
          "name": "simplify",
          "allowNo": true,
          "type": "boolean"
        },
        "id": {
          "char": "i",
          "exclusive": [
            "name",
            "dxid"
          ],
          "name": "id",
          "hasDynamicHelp": false,
          "multiple": false,
          "type": "option"
        },
        "dxid": {
          "char": "x",
          "description": "dxid",
          "name": "dxid",
          "hasDynamicHelp": false,
          "multiple": false,
          "type": "option"
        },
        "name": {
          "char": "n",
          "name": "name",
          "hasDynamicHelp": false,
          "multiple": false,
          "type": "option"
        },
        "git": {
          "description": "commit the changes to git",
          "name": "git",
          "allowNo": true,
          "type": "boolean"
        }
      },
      "hasDynamicHelp": false,
      "hiddenAliases": [],
      "id": "campaign:push",
      "pluginAlias": "@proca/widget",
      "pluginName": "@proca/widget",
      "pluginType": "core",
      "strict": true,
      "isESM": true,
      "relativePath": [
        "bin",
        "commands",
        "campaign",
        "push.mjs"
      ]
    },
    "widget:build": {
      "aliases": [],
      "args": {
        "id_name_dxid": {
          "description": "it's better to use -i <id> or -x <dxid> or -n <name>, but you can for convenience",
          "hidden": true,
          "name": "id_name_dxid"
        }
      },
      "description": "build the widget",
      "flags": {
        "json": {
          "description": "Format output as json",
          "exclusive": [
            "human",
            "csv"
          ],
          "helpGroup": "OUTPUT",
          "name": "json",
          "allowNo": false,
          "type": "boolean"
        },
        "env": {
          "description": "allow to switch between configurations (server or users)",
          "name": "env",
          "default": "default",
          "hasDynamicHelp": false,
          "multiple": false,
          "type": "option"
        },
        "human": {
          "description": "Format output to be read on screen by a human [default]",
          "helpGroup": "OUTPUT",
          "name": "human",
          "allowNo": false,
          "type": "boolean"
        },
        "csv": {
          "description": "Format output as csv",
          "helpGroup": "OUTPUT",
          "name": "csv",
          "allowNo": false,
          "type": "boolean"
        },
        "simplify": {
          "description": "flatten and filter to output only the most important attributes, mostly relevant for json",
          "helpGroup": "OUTPUT",
          "name": "simplify",
          "allowNo": true,
          "type": "boolean"
        },
        "id": {
          "char": "i",
          "name": "id",
          "required": true,
          "hasDynamicHelp": false,
          "multiple": false,
          "type": "option"
        },
        "dxid": {
          "char": "x",
          "description": "dxid",
          "name": "dxid",
          "hasDynamicHelp": false,
          "multiple": false,
          "type": "option"
        },
        "name": {
          "char": "n",
          "charAliases": [
            "o"
          ],
          "description": "name",
          "name": "name",
          "hasDynamicHelp": false,
          "helpValue": "<the_short_name>",
          "multiple": false,
          "type": "option"
        }
      },
      "hasDynamicHelp": false,
      "hiddenAliases": [],
      "id": "widget:build",
      "pluginAlias": "@proca/widget",
      "pluginName": "@proca/widget",
      "pluginType": "core",
      "strict": true,
      "enableJsonFlag": true,
      "hooks": {},
      "isESM": true,
      "relativePath": [
        "bin",
        "commands",
        "widget",
        "build.mjs"
      ]
    },
    "widget:pull": {
      "aliases": [],
      "args": {
        "id_name_dxid": {
          "description": "it's better to use -i <id> or -x <dxid> or -n <name>, but you can for convenience",
          "hidden": true,
          "name": "id_name_dxid"
        }
      },
      "description": "pull the widget (and campaign) configuration from the server",
      "examples": [
        "<%= config.bin %> <%= command.id %> -o <organisation>"
      ],
      "flags": {
        "json": {
          "description": "Format output as json",
          "exclusive": [
            "human",
            "csv"
          ],
          "helpGroup": "OUTPUT",
          "name": "json",
          "allowNo": false,
          "type": "boolean"
        },
        "env": {
          "description": "allow to switch between configurations (server or users)",
          "name": "env",
          "default": "default",
          "hasDynamicHelp": false,
          "multiple": false,
          "type": "option"
        },
        "human": {
          "description": "Format output to be read on screen by a human [default]",
          "helpGroup": "OUTPUT",
          "name": "human",
          "allowNo": false,
          "type": "boolean"
        },
        "csv": {
          "description": "Format output as csv",
          "helpGroup": "OUTPUT",
          "name": "csv",
          "allowNo": false,
          "type": "boolean"
        },
        "simplify": {
          "description": "flatten and filter to output only the most important attributes, mostly relevant for json",
          "helpGroup": "OUTPUT",
          "name": "simplify",
          "allowNo": true,
          "type": "boolean"
        },
        "id": {
          "char": "i",
          "exclusive": [
            "name",
            "dxid"
          ],
          "name": "id",
          "hasDynamicHelp": false,
          "multiple": false,
          "type": "option"
        },
        "dxid": {
          "char": "x",
          "description": "dxid",
          "name": "dxid",
          "hasDynamicHelp": false,
          "multiple": false,
          "type": "option"
        },
        "name": {
          "char": "n",
          "charAliases": [
            "o"
          ],
          "description": "name",
          "name": "name",
          "hasDynamicHelp": false,
          "helpValue": "<the_short_name>",
          "multiple": false,
          "type": "option"
        },
        "campaign": {
          "name": "campaign",
          "allowNo": true,
          "type": "boolean"
        },
        "git": {
          "description": "commit the changes to git",
          "name": "git",
          "allowNo": true,
          "type": "boolean"
        }
      },
      "hasDynamicHelp": false,
      "hiddenAliases": [],
      "id": "widget:pull",
      "pluginAlias": "@proca/widget",
      "pluginName": "@proca/widget",
      "pluginType": "core",
      "strict": true,
      "isESM": true,
      "relativePath": [
        "bin",
        "commands",
        "widget",
        "pull.mjs"
      ]
    },
    "widget:push": {
      "aliases": [],
      "args": {
        "id_name_dxid": {
          "description": "it's better to use -i <id> or -x <dxid> or -n <name>, but you can for convenience",
          "hidden": true,
          "name": "id_name_dxid"
        }
      },
      "description": "push to the server the local configuration of the widget",
      "examples": [
        "<%= config.bin %> <%= command.id %> -o <organisation>"
      ],
      "flags": {
        "json": {
          "description": "Format output as json",
          "exclusive": [
            "human",
            "csv"
          ],
          "helpGroup": "OUTPUT",
          "name": "json",
          "allowNo": false,
          "type": "boolean"
        },
        "env": {
          "description": "allow to switch between configurations (server or users)",
          "name": "env",
          "default": "default",
          "hasDynamicHelp": false,
          "multiple": false,
          "type": "option"
        },
        "human": {
          "description": "Format output to be read on screen by a human [default]",
          "helpGroup": "OUTPUT",
          "name": "human",
          "allowNo": false,
          "type": "boolean"
        },
        "csv": {
          "description": "Format output as csv",
          "helpGroup": "OUTPUT",
          "name": "csv",
          "allowNo": false,
          "type": "boolean"
        },
        "simplify": {
          "description": "flatten and filter to output only the most important attributes, mostly relevant for json",
          "helpGroup": "OUTPUT",
          "name": "simplify",
          "allowNo": true,
          "type": "boolean"
        },
        "id": {
          "char": "i",
          "name": "id",
          "hasDynamicHelp": false,
          "multiple": false,
          "type": "option"
        },
        "dxid": {
          "char": "x",
          "description": "dxid",
          "name": "dxid",
          "hasDynamicHelp": false,
          "multiple": false,
          "type": "option"
        },
        "name": {
          "char": "n",
          "charAliases": [
            "o"
          ],
          "description": "name",
          "name": "name",
          "hasDynamicHelp": false,
          "helpValue": "<the_short_name>",
          "multiple": false,
          "type": "option"
        },
        "campaign": {
          "char": "c",
          "description": "push all the widgets of that campaign [WIP]",
          "name": "campaign",
          "hasDynamicHelp": false,
          "multiple": false,
          "type": "option"
        },
        "git": {
          "description": "commit the changes to git",
          "name": "git",
          "allowNo": true,
          "type": "boolean"
        }
      },
      "hasDynamicHelp": false,
      "hiddenAliases": [],
      "id": "widget:push",
      "pluginAlias": "@proca/widget",
      "pluginName": "@proca/widget",
      "pluginType": "core",
      "strict": true,
      "isESM": true,
      "relativePath": [
        "bin",
        "commands",
        "widget",
        "push.mjs"
      ]
    },
    "widget:serve": {
      "aliases": [],
      "args": {
        "id_name_dxid": {
          "description": "it's better to use -i <id> or -x <dxid> or -n <name>, but you can for convenience",
          "hidden": true,
          "name": "id_name_dxid"
        }
      },
      "description": "preview the widget",
      "flags": {
        "json": {
          "description": "Format output as json",
          "exclusive": [
            "human",
            "csv"
          ],
          "helpGroup": "OUTPUT",
          "name": "json",
          "allowNo": false,
          "type": "boolean"
        },
        "env": {
          "description": "allow to switch between configurations (server or users)",
          "name": "env",
          "default": "default",
          "hasDynamicHelp": false,
          "multiple": false,
          "type": "option"
        },
        "human": {
          "description": "Format output to be read on screen by a human [default]",
          "helpGroup": "OUTPUT",
          "name": "human",
          "allowNo": false,
          "type": "boolean"
        },
        "csv": {
          "description": "Format output as csv",
          "helpGroup": "OUTPUT",
          "name": "csv",
          "allowNo": false,
          "type": "boolean"
        },
        "simplify": {
          "description": "flatten and filter to output only the most important attributes, mostly relevant for json",
          "helpGroup": "OUTPUT",
          "name": "simplify",
          "allowNo": true,
          "type": "boolean"
        },
        "id": {
          "char": "i",
          "exclusive": [
            "name",
            "dxid"
          ],
          "name": "id",
          "hasDynamicHelp": false,
          "multiple": false,
          "type": "option"
        },
        "dxid": {
          "char": "x",
          "description": "dxid",
          "name": "dxid",
          "hasDynamicHelp": false,
          "multiple": false,
          "type": "option"
        },
        "name": {
          "char": "n",
          "charAliases": [
            "o"
          ],
          "description": "name",
          "name": "name",
          "hasDynamicHelp": false,
          "helpValue": "<the_short_name>",
          "multiple": false,
          "type": "option"
        }
      },
      "hasDynamicHelp": false,
      "hiddenAliases": [],
      "id": "widget:serve",
      "pluginAlias": "@proca/widget",
      "pluginName": "@proca/widget",
      "pluginType": "core",
      "strict": true,
      "enableJsonFlag": true,
      "hooks": {},
      "isESM": true,
      "relativePath": [
        "bin",
        "commands",
        "widget",
        "serve.mjs"
      ]
    },
    "git:status": {
      "aliases": [],
      "args": {},
      "flags": {
        "json": {
          "description": "Format output as json",
          "exclusive": [
            "human",
            "csv"
          ],
          "helpGroup": "OUTPUT",
          "name": "json",
          "allowNo": false,
          "type": "boolean"
        },
        "env": {
          "description": "allow to switch between configurations (server or users)",
          "name": "env",
          "default": "default",
          "hasDynamicHelp": false,
          "multiple": false,
          "type": "option"
        },
        "human": {
          "description": "Format output to be read on screen by a human [default]",
          "helpGroup": "OUTPUT",
          "name": "human",
          "allowNo": false,
          "type": "boolean"
        },
        "csv": {
          "description": "Format output as csv",
          "helpGroup": "OUTPUT",
          "name": "csv",
          "allowNo": false,
          "type": "boolean"
        },
        "simplify": {
          "description": "flatten and filter to output only the most important attributes, mostly relevant for json",
          "helpGroup": "OUTPUT",
          "name": "simplify",
          "allowNo": true,
          "type": "boolean"
        }
      },
      "hasDynamicHelp": false,
      "hiddenAliases": [],
      "id": "git:status",
      "pluginAlias": "@proca/widget",
      "pluginName": "@proca/widget",
      "pluginType": "core",
      "strict": true,
      "isESM": true,
      "relativePath": [
        "bin",
        "commands",
        "git",
        "status.mjs"
      ]
    }
  },
  "version": "1.1.0"
}